matrix_atithmetic/__init__.py
matrix_atithmetic/mostoflogic.py
matrix_arithmetic_0.1.2-0.1.2.dist-info/LICENSE.txt
matrix_arithmetic_0.1.2-0.1.2.dist-info/METADATA
matrix_arithmetic_0.1.2-0.1.2.dist-info/WHEEL
matrix_arithmetic_0.1.2-0.1.2.dist-info/top_level.txt
matrix_arithmetic_0.1.2-0.1.2.dist-info/RECORD
